nvidia_animation_graph/__init__.py
nvidia_animation_graph/animgraph_pb2.py
nvidia_animation_graph/animgraph_pb2.pyi
nvidia_animation_graph/animgraph_pb2_grpc.py
nvidia_animation_graph/messages_pb2.py
nvidia_animation_graph/messages_pb2.pyi
nvidia_animation_graph/messages_pb2_grpc.py
nvidia_animation_graph/py.typed
nvidia_animation_graph-1.1.0.dist-info/METADATA
nvidia_animation_graph-1.1.0.dist-info/WHEEL
nvidia_animation_graph-1.1.0.dist-info/RECORD
