Metadata-Version: 2.4
Name: nvidia-animation-graph
Version: 1.1.0
Summary: AnimationGraph gRPC protoypes and services.
Requires-Python: >=3.8
Requires-Dist: nvidia-ace~=1.0
